spark_pipelines/__init__.py
spark_pipelines/_version.py
spark_pipelines/pipelines.py
spark_pipelines/quality.py
spark_pipelines/quarantine.py
spark_pipelines/spark_pipelines.py
spark_pipelines/types.py
spark_pipelines/validators.py
spark_pipelines-1.6.8.dist-info/LICENSE
spark_pipelines-1.6.8.dist-info/METADATA
spark_pipelines-1.6.8.dist-info/WHEEL
spark_pipelines-1.6.8.dist-info/entry_points.txt
spark_pipelines-1.6.8.dist-info/top_level.txt
spark_pipelines-1.6.8.dist-info/RECORD
