Metadata-Version: 2.1
Name: spark-pipelines
Version: 1.6.8
Summary: A Python package for validating Spark DataFrames against data quality rules.
Home-page: https://github.com/NileshPise/spark_pipelines
Author: Nilesh Pise
Author-email: neil9190patil@gmail.com
License: MIT
Keywords: spark,data quality,validation,decorators
Classifier: Programming Language :: Python :: 3
Classifier: License :: OSI Approved :: MIT License
Classifier: Operating System :: OS Independent
Requires-Python: >=3.6
License-File: LICENSE
Provides-Extra: testing
Requires-Dist: pytest; extra == "testing"
Requires-Dist: pytest-cov; extra == "testing"
